imagesource/__init__.py
imagesource/base.py
imagesource/files.py
imagesource/static.py
imagesource/synchronized.py
imagesource/timedvideo.py
imagesource/video.py
ImageSource-1.1.dist-info/LICENSE
ImageSource-1.1.dist-info/METADATA
ImageSource-1.1.dist-info/WHEEL
ImageSource-1.1.dist-info/top_level.txt
ImageSource-1.1.dist-info/RECORD
