Metadata-Version: 2.1
Name: ImageSource
Version: 1.1
Summary: Image sequence abstraction for OpenCV.
Home-page: https://github.com/smidm/imagesource
Author: Matěj Šmíd
Author-email: m@matejsmid.cz
License: The MIT License
Keywords: image sequence video
Platform: UNKNOWN
Classifier: Development Status :: 5 - Production/Stable
Classifier: Intended Audience :: Science/Research
Classifier: Topic :: Scientific/Engineering :: Image Recognition
Classifier: License :: OSI Approved :: MIT License
Classifier: Programming Language :: Python :: 3
Classifier: Programming Language :: Python :: 3.7
Requires-Dist: joblib
Requires-Dist: numpy
Requires-Dist: opencv-python-headless
Requires-Dist: tqdm
